[
  {
    "title": "2025 Ještědská Odysea",
    "description": "Čas a prostor tvoří naší realitu a existence má svá neměnná pravidla.První sobotu v červnu se proto opět uvidíme na třináctém ročníku hudebního festivalu Ještědská odysea. Opět ve Sportovním areálu Vesec, na čtyřech pódiích a v plné síle!!! ",
    "date": "2025-05-31",
    "location": "Sportovní areál Vesec, Liberec",
    "locationUrl": "https://maps.app.goo.gl/y8zgiSpKRDCfQs9x6",
    "image": "/news/2024-06-01.webp",
    "imagePosition": "top",
    "link": "https://www.facebook.com/events/792961862955177/"
  },
  {
    "title": "Předprodej vstupenek",
    "description": "Předprodej zahájen. Kupte si vstupenku dopředu, ušetříte nějakou tu korunu na drinky a čas při příchodu na akci!",
    "link": "https://www.book-tickets.cz/?page=bookticket&event=140",
    "icon": "ticket"
  }
]
